{
  "Points": [
    {
      "Key": "Cape Breton Export",
      "Val": 563.5
    },
    {
      "Key": "East End Export (at East Bay)",
      "Val": 587.7
    },
    {
      "Key": "East End Export (at Sydney)",
      "Val": 262.2
    },
    {
      "Key": "Flow Into Metro",
      "Val": 408.2
    },
    {
      "Key": "Highlands Export",
      "Val": 39.3
    },
    {
      "Key": "Maritime Link Import",
      "Val": 207.8
    },
    {
      "Key": "NS Export",
      "Val": -23.2
    },
    {
      "Key": "Net Load",
      "Val": 1867
    },
    {
      "Key": "Onslow Import",
      "Val": 681.1
    },
    {
      "Key": "Onslow South",
      "Val": 617.1
    },
    {
      "Key": "Valley Import",
      "Val": 155.2
    },
    {
      "Key": "Western Import",
      "Val": 123.1
    },
    {
      "Key": "Wind Generation",
      "Val": 367.6
    }
  ],
  "Time": "2022-02-16T08:14:20Z"
}
