{
  "Points": [
    {
      "Key": "Cape Breton Export",
      "Val": 475.3
    },
    {
      "Key": "East End Export (at East Bay)",
      "Val": 449.8
    },
    {
      "Key": "East End Export (at Sydney)",
      "Val": 331
    },
    {
      "Key": "Flow Into Metro",
      "Val": 316.4
    },
    {
      "Key": "Highlands Export",
      "Val": -3.4
    },
    {
      "Key": "Maritime Link Import",
      "Val": 0
    },
    {
      "Key": "NS Export",
      "Val": -67.7
    },
    {
      "Key": "Net Load",
      "Val": 1257
    },
    {
      "Key": "Onslow Import",
      "Val": 522.8
    },
    {
      "Key": "Onslow South",
      "Val": 484.7
    },
    {
      "Key": "Valley Import",
      "Val": 113.8
    },
    {
      "Key": "Western Import",
      "Val": 109.8
    },
    {
      "Key": "Wind Generation",
      "Val": 77.4
    }
  ],
  "Time": "2021-10-20T10:32:15Z"
}
