{
  "Points": [
    {
      "Key": "Cape Breton Export",
      "Val": 109.7
    },
    {
      "Key": "East End Export (at East Bay)",
      "Val": 263
    },
    {
      "Key": "East End Export (at Sydney)",
      "Val": 120.2
    },
    {
      "Key": "Flow Into Metro",
      "Val": 235.8
    },
    {
      "Key": "Highlands Export",
      "Val": -3.3
    },
    {
      "Key": "Maritime Link Import",
      "Val": 40.8
    },
    {
      "Key": "NS Export",
      "Val": -182.9
    },
    {
      "Key": "Net Load",
      "Val": 1114.7
    },
    {
      "Key": "Onslow Import",
      "Val": 175.6
    },
    {
      "Key": "Onslow South",
      "Val": 340.9
    },
    {
      "Key": "Valley Import",
      "Val": 80.4
    },
    {
      "Key": "Western Import",
      "Val": 73.1
    },
    {
      "Key": "Wind Generation",
      "Val": 310.6
    }
  ],
  "Time": "2022-06-11T01:12:00Z"
}
