{
  "Points": [
    {
      "Key": "Cape Breton Export",
      "Val": 850.1
    },
    {
      "Key": "East End Export (at East Bay)",
      "Val": 725.4
    },
    {
      "Key": "East End Export (at Sydney)",
      "Val": 439.5
    },
    {
      "Key": "Flow Into Metro",
      "Val": 585.3
    },
    {
      "Key": "Highlands Export",
      "Val": 45.1
    },
    {
      "Key": "Maritime Link Import",
      "Val": 160
    },
    {
      "Key": "NS Export",
      "Val": -1.5
    },
    {
      "Key": "Net Load",
      "Val": 1833.7
    },
    {
      "Key": "Onslow Import",
      "Val": 970.3
    },
    {
      "Key": "Onslow South",
      "Val": 845.3
    },
    {
      "Key": "Valley Import",
      "Val": 165.6
    },
    {
      "Key": "Western Import",
      "Val": 133.3
    },
    {
      "Key": "Wind Generation",
      "Val": 69.9
    }
  ],
  "Time": "2023-02-28T01:49:40Z"
}
