{
  "Points": [
    {
      "Key": "Cape Breton Export",
      "Val": 434.2
    },
    {
      "Key": "East End Export (at East Bay)",
      "Val": 516.2
    },
    {
      "Key": "East End Export (at Sydney)",
      "Val": 167
    },
    {
      "Key": "Flow Into Metro",
      "Val": 398.7
    },
    {
      "Key": "Highlands Export",
      "Val": -4.1
    },
    {
      "Key": "Maritime Link Import",
      "Val": 247.3
    },
    {
      "Key": "NS Export",
      "Val": -10.3
    },
    {
      "Key": "Net Load",
      "Val": 1395.7
    },
    {
      "Key": "Onslow Import",
      "Val": 587.8
    },
    {
      "Key": "Onslow South",
      "Val": 547.4
    },
    {
      "Key": "Valley Import",
      "Val": 99.5
    },
    {
      "Key": "Western Import",
      "Val": 82.9
    },
    {
      "Key": "Wind Generation",
      "Val": 249.7
    }
  ],
  "Time": "2022-12-18T04:02:50Z"
}
