{
  "Points": [
    {
      "Key": "Cape Breton Export",
      "Val": 480.6
    },
    {
      "Key": "East End Export (at East Bay)",
      "Val": 471.2
    },
    {
      "Key": "East End Export (at Sydney)",
      "Val": 318
    },
    {
      "Key": "Flow Into Metro",
      "Val": 496.4
    },
    {
      "Key": "Highlands Export",
      "Val": 92.5
    },
    {
      "Key": "Maritime Link Import",
      "Val": 160.2
    },
    {
      "Key": "NS Export",
      "Val": -106.3
    },
    {
      "Key": "Net Load",
      "Val": 1891.8
    },
    {
      "Key": "Onslow Import",
      "Val": 657.5
    },
    {
      "Key": "Onslow South",
      "Val": 707.3
    },
    {
      "Key": "Valley Import",
      "Val": 140.6
    },
    {
      "Key": "Western Import",
      "Val": 103.6
    },
    {
      "Key": "Wind Generation",
      "Val": 415.5
    }
  ],
  "Time": "2023-02-07T11:22:30Z"
}
