{
  "Points": [
    {
      "Key": "Cape Breton Export",
      "Val": 288
    },
    {
      "Key": "East End Export (at East Bay)",
      "Val": 337.8
    },
    {
      "Key": "East End Export (at Sydney)",
      "Val": 177.5
    },
    {
      "Key": "Flow Into Metro",
      "Val": 387.7
    },
    {
      "Key": "Highlands Export",
      "Val": 39
    },
    {
      "Key": "Maritime Link Import",
      "Val": 28
    },
    {
      "Key": "NS Export",
      "Val": -161.7
    },
    {
      "Key": "Net Load",
      "Val": 1519.2
    },
    {
      "Key": "Onslow Import",
      "Val": 406.8
    },
    {
      "Key": "Onslow South",
      "Val": 523.8
    },
    {
      "Key": "Valley Import",
      "Val": 95.1
    },
    {
      "Key": "Western Import",
      "Val": 69.4
    },
    {
      "Key": "Wind Generation",
      "Val": 382.2
    }
  ],
  "Time": "2022-03-02T07:53:30Z"
}
