{
  "Points": [
    {
      "Key": "Cape Breton Export",
      "Val": 434.5
    },
    {
      "Key": "East End Export (at East Bay)",
      "Val": 573.2
    },
    {
      "Key": "East End Export (at Sydney)",
      "Val": 154.9
    },
    {
      "Key": "Flow Into Metro",
      "Val": 312.4
    },
    {
      "Key": "Highlands Export",
      "Val": 66.2
    },
    {
      "Key": "Maritime Link Import",
      "Val": 261
    },
    {
      "Key": "NS Export",
      "Val": -172.9
    },
    {
      "Key": "Net Load",
      "Val": 1548.5
    },
    {
      "Key": "Onslow Import",
      "Val": 457.2
    },
    {
      "Key": "Onslow South",
      "Val": 520.3
    },
    {
      "Key": "Valley Import",
      "Val": 123.1
    },
    {
      "Key": "Western Import",
      "Val": 128.1
    },
    {
      "Key": "Wind Generation",
      "Val": 56.4
    }
  ],
  "Time": "2023-01-29T15:12:00Z"
}
