{
  "Points": [
    {
      "Key": "Cape Breton Export",
      "Val": 528.4
    },
    {
      "Key": "East End Export (at East Bay)",
      "Val": 495.5
    },
    {
      "Key": "East End Export (at Sydney)",
      "Val": 187.6
    },
    {
      "Key": "Flow Into Metro",
      "Val": 656
    },
    {
      "Key": "Highlands Export",
      "Val": -3
    },
    {
      "Key": "Maritime Link Import",
      "Val": 159.9
    },
    {
      "Key": "NS Export",
      "Val": -213.3
    },
    {
      "Key": "Net Load",
      "Val": 1796.8
    },
    {
      "Key": "Onslow Import",
      "Val": 733.9
    },
    {
      "Key": "Onslow South",
      "Val": 874.5
    },
    {
      "Key": "Valley Import",
      "Val": 137.1
    },
    {
      "Key": "Western Import",
      "Val": 107.8
    },
    {
      "Key": "Wind Generation",
      "Val": 405.4
    }
  ],
  "Time": "2022-12-13T15:02:30Z"
}
