{
  "Points": [
    {
      "Key": "Cape Breton Export",
      "Val": 183.6
    },
    {
      "Key": "East End Export (at East Bay)",
      "Val": 211
    },
    {
      "Key": "East End Export (at Sydney)",
      "Val": 22.2
    },
    {
      "Key": "Flow Into Metro",
      "Val": 308.7
    },
    {
      "Key": "Highlands Export",
      "Val": -3.7
    },
    {
      "Key": "Maritime Link Import",
      "Val": 46.8
    },
    {
      "Key": "NS Export",
      "Val": -186.8
    },
    {
      "Key": "Net Load",
      "Val": 1513.4
    },
    {
      "Key": "Onslow Import",
      "Val": 296.7
    },
    {
      "Key": "Onslow South",
      "Val": 439.8
    },
    {
      "Key": "Valley Import",
      "Val": 98.2
    },
    {
      "Key": "Western Import",
      "Val": 71.6
    },
    {
      "Key": "Wind Generation",
      "Val": 482.2
    }
  ],
  "Time": "2021-11-17T13:39:55Z"
}
