{
  "Points": [
    {
      "Key": "Cape Breton Export",
      "Val": 327.3
    },
    {
      "Key": "East End Export (at East Bay)",
      "Val": 345.2
    },
    {
      "Key": "East End Export (at Sydney)",
      "Val": 207
    },
    {
      "Key": "Flow Into Metro",
      "Val": 205.8
    },
    {
      "Key": "Highlands Export",
      "Val": 95.3
    },
    {
      "Key": "Maritime Link Import",
      "Val": 41.3
    },
    {
      "Key": "NS Export",
      "Val": -3.8
    },
    {
      "Key": "Net Load",
      "Val": 1088.4
    },
    {
      "Key": "Onslow Import",
      "Val": 376.1
    },
    {
      "Key": "Onslow South",
      "Val": 314.2
    },
    {
      "Key": "Valley Import",
      "Val": 51.9
    },
    {
      "Key": "Western Import",
      "Val": 60.7
    },
    {
      "Key": "Wind Generation",
      "Val": 125.7
    }
  ],
  "Time": "2023-01-14T08:28:50Z"
}
