{
  "Points": [
    {
      "Key": "Cape Breton Export",
      "Val": 272.5
    },
    {
      "Key": "East End Export (at East Bay)",
      "Val": 369.8
    },
    {
      "Key": "East End Export (at Sydney)",
      "Val": 219.9
    },
    {
      "Key": "Flow Into Metro",
      "Val": 243.4
    },
    {
      "Key": "Highlands Export",
      "Val": -3.6
    },
    {
      "Key": "Maritime Link Import",
      "Val": 0
    },
    {
      "Key": "NS Export",
      "Val": -120.2
    },
    {
      "Key": "Net Load",
      "Val": 1145.5
    },
    {
      "Key": "Onslow Import",
      "Val": 329.5
    },
    {
      "Key": "Onslow South",
      "Val": 395
    },
    {
      "Key": "Valley Import",
      "Val": 112.9
    },
    {
      "Key": "Western Import",
      "Val": 105
    },
    {
      "Key": "Wind Generation",
      "Val": 149.7
    }
  ],
  "Time": "2022-06-22T19:12:10Z"
}
