{
  "Points": [
    {
      "Key": "Cape Breton Export",
      "Val": 346.1
    },
    {
      "Key": "East End Export (at East Bay)",
      "Val": 536.1
    },
    {
      "Key": "East End Export (at Sydney)",
      "Val": 224.9
    },
    {
      "Key": "Flow Into Metro",
      "Val": 218.1
    },
    {
      "Key": "Highlands Export",
      "Val": -4.6
    },
    {
      "Key": "Maritime Link Import",
      "Val": 155.8
    },
    {
      "Key": "NS Export",
      "Val": -5
    },
    {
      "Key": "Net Load",
      "Val": 1354.3
    },
    {
      "Key": "Onslow Import",
      "Val": 358.2
    },
    {
      "Key": "Onslow South",
      "Val": 335.7
    },
    {
      "Key": "Valley Import",
      "Val": 93.7
    },
    {
      "Key": "Western Import",
      "Val": 76.4
    },
    {
      "Key": "Wind Generation",
      "Val": 412.1
    }
  ],
  "Time": "2022-07-19T14:19:45Z"
}
