{
  "Points": [
    {
      "Key": "Cape Breton Export",
      "Val": 586.1
    },
    {
      "Key": "East End Export (at East Bay)",
      "Val": 490
    },
    {
      "Key": "East End Export (at Sydney)",
      "Val": 164.1
    },
    {
      "Key": "Flow Into Metro",
      "Val": 489.7
    },
    {
      "Key": "Highlands Export",
      "Val": 83.5
    },
    {
      "Key": "Maritime Link Import",
      "Val": 200.4
    },
    {
      "Key": "NS Export",
      "Val": -158
    },
    {
      "Key": "Net Load",
      "Val": 1572.7
    },
    {
      "Key": "Onslow Import",
      "Val": 675.9
    },
    {
      "Key": "Onslow South",
      "Val": 725.1
    },
    {
      "Key": "Valley Import",
      "Val": 148.3
    },
    {
      "Key": "Western Import",
      "Val": 133.3
    },
    {
      "Key": "Wind Generation",
      "Val": 168.6
    }
  ],
  "Time": "2023-02-15T08:12:50Z"
}
