[
  {
    "desc": {
      "cause": "Cause Being Investigated",
      "cluster": false,
      "cust_a": {
        "val": 35
      },
      "etr": "2023-08-19T09:00:00-0300",
      "start": "2023-08-19T03:03:00-0300"
    },
    "geom": {
      "a": [
        "ijbuGdbtyJik@pnDwBew@PmGnZwpB~RxA"
      ],
      "p": [
        "yecuGbjvyJ"
      ]
    },
    "id": "1",
    "title": "Outage Information"
  },
  {
    "desc": {
      "cause": "Cause Being Investigated",
      "cluster": false,
      "cust_a": {
        "val": 692
      },
      "etr": "2023-08-19T09:00:00-0300",
      "start": "2023-08-19T02:37:32-0300"
    },
    "geom": {
      "a": [
        "o}{tGdem`KuxPfbYc[j^ioMgy@{_CeqUr}KcsU|fBys@`dCif@vgHyoArqFziX"
      ],
      "p": [
        "uaouG~qn`K"
      ]
    },
    "id": "2",
    "title": "Outage Information"
  },
  {
    "desc": {
      "cause": "Cause Being Investigated",
      "cluster": false,
      "cust_a": {
        "masked": true,
        "val": 4
      },
      "etr": "2023-08-19T09:30:00-0300",
      "start": "2023-08-19T00:58:31-0300"
    },
    "geom": {
      "p": [
        "gjwmG|htiK"
      ]
    },
    "id": "3",
    "title": "Outage Information"
  },
  {
    "desc": {
      "cause": "Cause Being Investigated",
      "cluster": false,
      "cust_a": {
        "val": 5
      },
      "etr": "2023-08-19T09:00:00-0300",
      "start": "2023-08-19T00:17:47-0300"
    },
    "geom": {
      "a": [
        "gkmmGz~tiK_p@j~@uhAe`FOsFfr@~z@|fAllB"
      ],
      "p": [
        "efomG|usiK"
      ]
    },
    "id": "4",
    "title": "Outage Information"
  },
  {
    "desc": {
      "cause": "Trees On Line",
      "cluster": false,
      "cust_a": {
        "masked": true,
        "val": 4
      },
      "etr": "2023-08-20T16:00:00-0300",
      "start": "2023-08-17T10:13:00-0300"
    },
    "geom": {
      "p": [
        "ieruGhsw|J"
      ]
    },
    "id": "5",
    "title": "Outage Information"
  },
  {
    "desc": {
      "cause": "Cause Being Investigated",
      "cluster": false,
      "cust_a": {
        "masked": true,
        "val": 4
      },
      "etr": "2023-08-21T10:00:00-0300",
      "start": "2023-08-03T10:41:00-0300"
    },
    "geom": {
      "p": [
        "_v~{Gj{toJ"
      ]
    },
    "id": "6",
    "title": "Outage Information"
  }
]
