[
  {
    "desc": {
      "cause": "Cause Being Investigated",
      "cluster": false,
      "cust_a": {
        "masked": true,
        "val": 4
      },
      "etr": "2024-07-23T19:00:00-0300",
      "start": "2024-07-23T15:00:00-0300"
    },
    "geom": {
      "p": [
        "omjvGxmw~J"
      ]
    },
    "id": "1",
    "title": "Outage Information"
  },
  {
    "desc": {
      "cause": "Cause Being Investigated",
      "cluster": false,
      "cust_a": {
        "val": 7
      },
      "etr": "2024-07-23T18:00:00-0300",
      "start": "2024-07-23T13:39:00-0300"
    },
    "geom": {
      "p": [
        "yaxoGtlxdK"
      ]
    },
    "id": "2",
    "title": "Outage Information"
  },
  {
    "desc": {
      "cause": "Cause Being Investigated",
      "cluster": false,
      "cust_a": {
        "masked": true,
        "val": 4
      },
      "etr": "2024-07-23T18:00:00-0300",
      "start": "2024-07-23T09:47:02-0300"
    },
    "geom": {
      "p": [
        "{`soGbttbK"
      ]
    },
    "id": "3",
    "title": "Outage Information"
  },
  {
    "desc": {
      "cause": "Cause Being Investigated",
      "cluster": false,
      "cust_a": {
        "masked": true,
        "val": 4
      },
      "etr": "2024-07-23T20:45:00-0300",
      "start": "2024-07-23T13:45:00-0300"
    },
    "geom": {
      "p": [
        "efduG|t|}J"
      ]
    },
    "id": "4",
    "title": "Outage Information"
  },
  {
    "desc": {
      "cause": "Cause Being Investigated",
      "cluster": false,
      "cust_a": {
        "masked": true,
        "val": 4
      },
      "etr": "2024-07-23T18:15:00-0300",
      "start": "2024-07-23T13:00:00-0300"
    },
    "geom": {
      "p": [
        "{s`yGngboJ"
      ]
    },
    "id": "5",
    "title": "Outage Information"
  },
  {
    "desc": {
      "cause": "Cause Being Investigated",
      "cluster": false,
      "cust_a": {
        "masked": true,
        "val": 4
      },
      "etr": "2024-07-23T17:00:00-0300",
      "start": "2024-07-23T12:47:00-0300"
    },
    "geom": {
      "p": [
        "cweyGvernJ"
      ]
    },
    "id": "6",
    "title": "Outage Information"
  }
]
