[
  {
    "desc": {
      "cause": "High Winds",
      "cluster": false,
      "cust_a": {
        "masked": true,
        "val": 4
      },
      "etr": "2023-02-04T23:00:00-0400",
      "start": "2023-02-04T03:15:56-0400"
    },
    "geom": {
      "p": [
        "ikdpG~soaK"
      ]
    },
    "id": "1",
    "title": "Outage Information"
  },
  {
    "desc": {
      "cause": "High Winds",
      "cluster": false,
      "cust_a": {
        "masked": true,
        "val": 4
      },
      "etr": "2023-02-04T23:00:00-0400",
      "start": "2023-02-04T02:57:21-0400"
    },
    "geom": {
      "p": [
        "cfxyG~n_sJ"
      ]
    },
    "id": "10",
    "title": "Outage Information"
  },
  {
    "desc": {
      "cause": "High Winds",
      "cluster": false,
      "cust_a": {
        "masked": true,
        "val": 4
      },
      "etr": "2023-02-04T23:00:00-0400",
      "start": "2023-02-04T02:58:14-0400"
    },
    "geom": {
      "p": [
        "{l|yGhncsJ"
      ]
    },
    "id": "11",
    "title": "Outage Information"
  },
  {
    "desc": {
      "cause": "High Winds",
      "cluster": false,
      "cust_a": {
        "masked": true,
        "val": 4
      },
      "etr": "2023-02-04T23:00:00-0400",
      "start": "2023-02-04T02:59:17-0400"
    },
    "geom": {
      "p": [
        "wsroGzcdgK"
      ]
    },
    "id": "12",
    "title": "Outage Information"
  },
  {
    "desc": {
      "cause": "High Winds",
      "cluster": false,
      "cust_a": {
        "masked": true,
        "val": 4
      },
      "etr": "2023-02-04T23:00:00-0400",
      "start": "2023-02-04T02:53:04-0400"
    },
    "geom": {
      "p": [
        "c}azGvhesJ"
      ]
    },
    "id": "14",
    "title": "Outage Information"
  },
  {
    "desc": {
      "cluster": true,
      "cust_a": {
        "val": 5
      },
      "n_out": 2,
      "outages": [
        {
          "cause": "High Winds",
          "cluster": false,
          "cust_a": {
            "masked": true,
            "val": 4
          },
          "etr": "2023-02-04T23:00:00-0400",
          "start": "2023-02-04T02:51:04-0400"
        },
        {
          "cause": "High Winds",
          "cluster": false,
          "cust_a": {
            "masked": true,
            "val": 4
          },
          "etr": "2023-02-04T23:00:00-0400",
          "start": "2023-02-04T01:42:44-0400"
        }
      ]
    },
    "geom": {
      "p": [
        "omxwGdpglJ"
      ]
    },
    "id": "14-1",
    "title": "Area Outage"
  },
  {
    "desc": {
      "cluster": true,
      "cust_a": {
        "val": 5
      },
      "n_out": 2,
      "outages": [
        {
          "cause": "Cause Being Investigated",
          "cluster": false,
          "cust_a": {
            "masked": true,
            "val": 4
          },
          "etr": "2023-02-04T23:00:00-0400",
          "start": "2023-02-03T19:42:20-0400"
        },
        {
          "cause": "Cause Being Investigated",
          "cluster": false,
          "cust_a": {
            "masked": true,
            "val": 4
          },
          "etr": "2023-02-04T23:00:00-0400",
          "start": "2023-02-03T19:37:28-0400"
        }
      ]
    },
    "geom": {
      "p": [
        "qbzjGn{erK"
      ]
    },
    "id": "14-2",
    "title": "Area Outage"
  },
  {
    "desc": {
      "cluster": true,
      "cust_a": {
        "masked": true,
        "val": 4
      },
      "n_out": 2,
      "outages": [
        {
          "cause": "High Winds",
          "cluster": false,
          "cust_a": {
            "masked": true,
            "val": 4
          },
          "etr": "2023-02-04T23:00:00-0400",
          "start": "2023-02-04T01:11:38-0400"
        },
        {
          "cause": "High Winds",
          "cluster": false,
          "cust_a": {
            "masked": true,
            "val": 4
          },
          "etr": "2023-02-04T23:00:00-0400",
          "start": "2023-02-04T01:03:40-0400"
        }
      ]
    },
    "geom": {
      "p": [
        "{d{xGvqopJ"
      ]
    },
    "id": "14-3",
    "title": "Area Outage"
  },
  {
    "desc": {
      "cause": "High Winds",
      "cluster": false,
      "cust_a": {
        "val": 12
      },
      "etr": "2023-02-04T23:00:00-0400",
      "start": "2023-02-04T02:43:50-0400"
    },
    "geom": {
      "a": [
        "qwtoG|cdgK_HhLeTjGd]uT"
      ],
      "p": [
        "sduoGpodgK"
      ]
    },
    "id": "15",
    "title": "Outage Information"
  },
  {
    "desc": {
      "cause": "Damage to Overhead Equipment",
      "cluster": false,
      "cust_a": {
        "val": 250
      },
      "etr": "2023-02-04T05:00:00-0400",
      "start": "2023-02-04T02:25:33-0400"
    },
    "geom": {
      "a": [
        "ikvxG~i|mJmZiJ}a@eg@u`AiwAwD_hBvQshDbA]ho@oP|Dl@xJ`Ozm@j~K"
      ],
      "p": [
        "krxxGxjumJ"
      ]
    },
    "id": "16",
    "title": "Outage Information"
  },
  {
    "desc": {
      "cause": "High Winds",
      "cluster": false,
      "cust_a": {
        "masked": true,
        "val": 4
      },
      "etr": "2023-02-04T23:00:00-0400",
      "start": "2023-02-04T02:42:44-0400"
    },
    "geom": {
      "p": [
        "q~pzGjqxrJ"
      ]
    },
    "id": "17",
    "title": "Outage Information"
  },
  {
    "desc": {
      "cause": "High Winds",
      "cluster": false,
      "cust_a": {
        "val": 5
      },
      "etr": "2023-02-04T23:00:00-0400",
      "start": "2023-02-04T02:03:46-0400"
    },
    "geom": {
      "p": [
        "uzxwG||flJ"
      ]
    },
    "id": "18",
    "title": "Outage Information"
  },
  {
    "desc": {
      "cause": "High Winds",
      "cluster": false,
      "cust_a": {
        "val": 148
      },
      "etr": "2023-02-04T14:00:00-0400",
      "start": "2023-02-04T01:10:05-0400"
    },
    "geom": {
      "a": [
        "kqqoGlwigKcqE|jGogE_uAkBmPuE}gI`P_uB~RoRrYzS~cJ`xG"
      ],
      "p": [
        "_tyoGv{igK"
      ]
    },
    "id": "19",
    "title": "Outage Information"
  },
  {
    "desc": {
      "cause": "High Winds",
      "cluster": false,
      "cust_a": {
        "masked": true,
        "val": 4
      },
      "etr": "2023-02-04T23:00:00-0400",
      "start": "2023-02-04T03:11:42-0400"
    },
    "geom": {
      "p": [
        "se`zGbdesJ"
      ]
    },
    "id": "2",
    "title": "Outage Information"
  },
  {
    "desc": {
      "cause": "High Winds",
      "cluster": false,
      "cust_a": {
        "masked": true,
        "val": 4
      },
      "etr": "2023-02-04T23:00:00-0400",
      "start": "2023-02-04T01:10:05-0400"
    },
    "geom": {
      "p": [
        "s{toG~`bgK"
      ]
    },
    "id": "20",
    "title": "Outage Information"
  },
  {
    "desc": {
      "cause": "High Winds",
      "cluster": false,
      "cust_a": {
        "masked": true,
        "val": 4
      },
      "etr": "2023-02-04T23:00:00-0400",
      "start": "2023-02-04T00:30:29-0400"
    },
    "geom": {
      "p": [
        "olipGn~o`K"
      ]
    },
    "id": "22",
    "title": "Outage Information"
  },
  {
    "desc": {
      "cause": "High Winds",
      "cluster": false,
      "cust_a": {
        "masked": true,
        "val": 4
      },
      "etr": "2023-02-04T23:00:00-0400",
      "start": "2023-02-04T02:22:46-0400"
    },
    "geom": {
      "p": [
        "khjpG|vl`K"
      ]
    },
    "id": "23",
    "title": "Outage Information"
  },
  {
    "desc": {
      "cause": "High Winds",
      "cluster": false,
      "cust_a": {
        "val": 8
      },
      "etr": "2023-02-04T23:00:00-0400",
      "start": "2023-02-04T00:50:16-0400"
    },
    "geom": {
      "p": [
        "essxG`fhnJ"
      ]
    },
    "id": "26",
    "title": "Outage Information"
  },
  {
    "desc": {
      "cause": "High Winds",
      "cluster": false,
      "cust_a": {
        "val": 187
      },
      "etr": "2023-02-04T14:00:00-0400",
      "start": "2023-02-04T01:26:26-0400"
    },
    "geom": {
      "a": [
        "{jbvGvqbaKiEjWqA|EeI|CmrAulDyDaLeGwWyCed@zTme@xfAthDrZdpA"
      ],
      "p": [
        "sidvG|e_aK"
      ]
    },
    "id": "27",
    "title": "Outage Information"
  },
  {
    "desc": {
      "cause": "High Winds",
      "cluster": false,
      "cust_a": {
        "masked": true,
        "val": 4
      },
      "etr": "2023-02-04T23:00:00-0400",
      "start": "2023-02-04T00:05:19-0400"
    },
    "geom": {
      "p": [
        "ixcoGftigK"
      ]
    },
    "id": "28",
    "title": "Outage Information"
  },
  {
    "desc": {
      "cause": "High Winds",
      "cluster": false,
      "cust_a": {
        "masked": true,
        "val": 4
      },
      "etr": "2023-02-04T23:00:00-0400",
      "start": "2023-02-04T01:17:18-0400"
    },
    "geom": {
      "p": [
        "qaqnGz`ifK"
      ]
    },
    "id": "29",
    "title": "Outage Information"
  },
  {
    "desc": {
      "cause": "High Winds",
      "cluster": false,
      "cust_a": {
        "val": 12
      },
      "etr": "2023-02-04T23:00:00-0400",
      "start": "2023-02-03T23:27:15-0400"
    },
    "geom": {
      "p": [
        "sz{lGvdurK"
      ]
    },
    "id": "3",
    "title": "Outage Information"
  },
  {
    "desc": {
      "cause": "High Winds",
      "cluster": false,
      "cust_a": {
        "masked": true,
        "val": 4
      },
      "etr": "2023-02-04T23:00:00-0400",
      "start": "2023-02-04T01:03:31-0400"
    },
    "geom": {
      "p": [
        "mkimGtfsrK"
      ]
    },
    "id": "31",
    "title": "Outage Information"
  },
  {
    "desc": {
      "cause": "High Winds",
      "cluster": false,
      "cust_a": {
        "val": 97
      },
      "etr": "2023-02-04T23:00:00-0400",
      "start": "2023-02-04T00:42:58-0400"
    },
    "geom": {
      "a": [
        "{`brGpjehKy@~LkJzC_GlAjGaa@|A]fH|BRvH"
      ],
      "p": [
        "gjbrGjnehK"
      ]
    },
    "id": "34",
    "title": "Outage Information"
  },
  {
    "desc": {
      "cause": "Cause Being Investigated",
      "cluster": false,
      "cust_a": {
        "masked": true,
        "val": 4
      },
      "etr": "2023-02-04T23:00:00-0400",
      "start": "2023-02-03T23:41:33-0400"
    },
    "geom": {
      "p": [
        "q`hhGfisoK"
      ]
    },
    "id": "35",
    "title": "Outage Information"
  },
  {
    "desc": {
      "cause": "Cause Being Investigated",
      "cluster": false,
      "cust_a": {
        "masked": true,
        "val": 4
      },
      "etr": "2023-02-04T23:00:00-0400",
      "start": "2023-02-03T23:26:07-0400"
    },
    "geom": {
      "p": [
        "gllsGplm}J"
      ]
    },
    "id": "36",
    "title": "Outage Information"
  },
  {
    "desc": {
      "cause": "Cause Being Investigated",
      "cluster": false,
      "cust_a": {
        "masked": true,
        "val": 4
      },
      "etr": "2023-02-04T23:00:00-0400",
      "start": "2023-02-03T21:58:48-0400"
    },
    "geom": {
      "p": [
        "qcyiGzhklK"
      ]
    },
    "id": "37",
    "title": "Outage Information"
  },
  {
    "desc": {
      "cause": "Cause Being Investigated",
      "cluster": false,
      "cust_a": {
        "masked": true,
        "val": 4
      },
      "etr": "2023-02-04T23:00:00-0400",
      "start": "2023-02-03T19:25:22-0400"
    },
    "geom": {
      "p": [
        "_`|kGtt~pK"
      ]
    },
    "id": "38",
    "title": "Outage Information"
  },
  {
    "desc": {
      "cause": "Cause Being Investigated",
      "cluster": false,
      "cust_a": {
        "val": 5
      },
      "etr": "2023-02-04T23:00:00-0400",
      "start": "2023-02-03T21:00:57-0400"
    },
    "geom": {
      "p": [
        "giarGt~dhK"
      ]
    },
    "id": "39",
    "title": "Outage Information"
  },
  {
    "desc": {
      "cause": "High Winds",
      "cluster": false,
      "cust_a": {
        "masked": true,
        "val": 4
      },
      "etr": "2023-02-04T23:00:00-0400",
      "start": "2023-02-04T02:51:10-0400"
    },
    "geom": {
      "p": [
        "m_auGbwx}J"
      ]
    },
    "id": "4",
    "title": "Outage Information"
  },
  {
    "desc": {
      "cause": "Cause Being Investigated",
      "cluster": false,
      "cust_a": {
        "masked": true,
        "val": 4
      },
      "etr": "2023-02-04T23:00:00-0400",
      "start": "2023-02-03T22:29:33-0400"
    },
    "geom": {
      "p": [
        "sg`rG`unhK"
      ]
    },
    "id": "40",
    "title": "Outage Information"
  },
  {
    "desc": {
      "cause": "High Winds",
      "cluster": false,
      "cust_a": {
        "masked": true,
        "val": 4
      },
      "etr": "2023-02-04T23:00:00-0400",
      "start": "2023-02-03T22:29:33-0400"
    },
    "geom": {
      "p": [
        "{_arGjkmhK"
      ]
    },
    "id": "41",
    "title": "Outage Information"
  },
  {
    "desc": {
      "cause": "High Winds",
      "cluster": false,
      "cust_a": {
        "masked": true,
        "val": 4
      },
      "etr": "2023-02-04T23:00:00-0400",
      "start": "2023-02-03T22:29:33-0400"
    },
    "geom": {
      "p": [
        "ud~qGd{thK"
      ]
    },
    "id": "42",
    "title": "Outage Information"
  },
  {
    "desc": {
      "cause": "High Winds",
      "cluster": false,
      "cust_a": {
        "masked": true,
        "val": 4
      },
      "etr": "2023-02-04T23:00:00-0400",
      "start": "2023-02-04T00:08:04-0400"
    },
    "geom": {
      "p": [
        "yd{xGdhqpJ"
      ]
    },
    "id": "43",
    "title": "Outage Information"
  },
  {
    "desc": {
      "cause": "Cause Being Investigated",
      "cluster": false,
      "cust_a": {
        "masked": true,
        "val": 4
      },
      "etr": "2023-02-04T23:00:00-0400",
      "start": "2023-02-03T23:46:25-0400"
    },
    "geom": {
      "p": [
        "o~_wGlgzpJ"
      ]
    },
    "id": "44",
    "title": "Outage Information"
  },
  {
    "desc": {
      "cause": "Cause Being Investigated",
      "cluster": false,
      "cust_a": {
        "masked": true,
        "val": 4
      },
      "etr": "2023-02-04T23:00:00-0400",
      "start": "2023-02-03T23:46:27-0400"
    },
    "geom": {
      "p": [
        "wk}xGj`lpJ"
      ]
    },
    "id": "45",
    "title": "Outage Information"
  },
  {
    "desc": {
      "cause": "Cause Being Investigated",
      "cluster": false,
      "cust_a": {
        "masked": true,
        "val": 4
      },
      "etr": "2023-02-05T16:45:00-0400",
      "start": "2023-02-03T09:44:00-0400"
    },
    "geom": {
      "p": [
        "g}vtG`bz`K"
      ]
    },
    "id": "46",
    "title": "Outage Information"
  },
  {
    "desc": {
      "cause": "Cause Being Investigated",
      "cluster": false,
      "cust_a": {
        "masked": true,
        "val": 4
      },
      "etr": "2023-02-04T21:00:00-0400",
      "start": "2023-02-03T16:08:27-0400"
    },
    "geom": {
      "p": [
        "}i~tG`{f`K"
      ]
    },
    "id": "47",
    "title": "Outage Information"
  },
  {
    "desc": {
      "cause": "High Winds",
      "cluster": false,
      "cust_a": {
        "masked": true,
        "val": 4
      },
      "etr": "2023-02-05T14:01:00-0400",
      "start": "2023-01-26T20:03:06-0400"
    },
    "geom": {
      "p": [
        "wsqjGd__qK"
      ]
    },
    "id": "49",
    "title": "Outage Information"
  },
  {
    "desc": {
      "cause": "High Winds",
      "cluster": false,
      "cust_a": {
        "val": 6
      },
      "etr": "2023-02-04T23:00:00-0400",
      "start": "2023-02-04T00:27:14-0400"
    },
    "geom": {
      "p": [
        "oj|lGhttrK"
      ]
    },
    "id": "5",
    "title": "Outage Information"
  },
  {
    "desc": {
      "cause": "Cause Being Investigated",
      "cluster": false,
      "cust_a": {
        "masked": true,
        "val": 4
      },
      "etr": "2023-02-04T08:30:00-0400",
      "start": "2023-02-03T16:57:51-0400"
    },
    "geom": {
      "p": [
        "yv~qGlfmgK"
      ]
    },
    "id": "52",
    "title": "Outage Information"
  },
  {
    "desc": {
      "cause": "Cause Being Investigated",
      "cluster": false,
      "cust_a": {
        "masked": true,
        "val": 4
      },
      "etr": "2023-02-04T23:00:00-0400",
      "start": "2023-02-03T23:08:18-0400"
    },
    "geom": {
      "p": [
        "mxuuGzd~|J"
      ]
    },
    "id": "6",
    "title": "Outage Information"
  },
  {
    "desc": {
      "cause": "High Winds",
      "cluster": false,
      "cust_a": {
        "val": 17
      },
      "etr": "2023-02-04T14:00:00-0400",
      "start": "2023-02-04T02:27:17-0400"
    },
    "geom": {
      "p": [
        "qpayGjl}lJ"
      ]
    },
    "id": "7",
    "title": "Outage Information"
  },
  {
    "desc": {
      "cause": "High Winds",
      "cluster": false,
      "cust_a": {
        "masked": true,
        "val": 4
      },
      "etr": "2023-02-04T23:00:00-0400",
      "start": "2023-02-04T02:11:47-0400"
    },
    "geom": {
      "p": [
        "ogeuGh_a~J"
      ]
    },
    "id": "8",
    "title": "Outage Information"
  }
]
