[
  {
    "desc": {
      "cause": "Cause Being Investigated",
      "cluster": false,
      "cust_a": {
        "val": 14
      },
      "etr": "2024-07-31T22:00:00-0300",
      "start": "2024-07-31T16:57:37-0300"
    },
    "geom": {
      "a": [
        "esmqGtpyaKmP~c@ar@nEzCqN`~@ed@PfH"
      ],
      "p": [
        "ornqGxfzaK"
      ]
    },
    "id": "1",
    "title": "Outage Information"
  },
  {
    "desc": {
      "cause": "Cause Being Investigated",
      "cluster": false,
      "cust_a": {
        "masked": true,
        "val": 4
      },
      "etr": "2024-07-31T22:00:00-0300",
      "start": "2024-07-31T17:09:00-0300"
    },
    "geom": {
      "p": [
        "{pdhG|proK"
      ]
    },
    "id": "2",
    "title": "Outage Information"
  },
  {
    "desc": {
      "cause": "Cause Being Investigated",
      "cluster": false,
      "cust_a": {
        "masked": true,
        "val": 4
      },
      "etr": "2024-07-31T21:15:00-0300",
      "start": "2024-07-31T17:14:34-0300"
    },
    "geom": {
      "p": [
        "itapGnlzkK"
      ]
    },
    "id": "3",
    "title": "Outage Information"
  },
  {
    "desc": {
      "cause": "Cause Being Investigated",
      "cluster": false,
      "cust_a": {
        "masked": true,
        "val": 4
      },
      "etr": "2024-07-31T20:15:00-0300",
      "start": "2024-07-31T15:09:11-0300"
    },
    "geom": {
      "p": [
        "abuxGtjxoJ"
      ]
    },
    "id": "4",
    "title": "Outage Information"
  },
  {
    "desc": {
      "cause": "Cause Being Investigated",
      "cluster": false,
      "cust_a": {
        "masked": true,
        "val": 4
      },
      "etr": "2024-07-31T18:00:00-0300",
      "start": "2024-07-31T14:42:03-0300"
    },
    "geom": {
      "p": [
        "oy}oGzpubK"
      ]
    },
    "id": "5",
    "title": "Outage Information"
  },
  {
    "desc": {
      "cause": "Cause Being Investigated",
      "cluster": false,
      "cust_a": {
        "masked": true,
        "val": 4
      },
      "etr": "2024-07-31T18:00:00-0300",
      "start": "2024-07-31T14:15:00-0300"
    },
    "geom": {
      "p": [
        "q_yuG`|{`K"
      ]
    },
    "id": "6",
    "title": "Outage Information"
  },
  {
    "desc": {
      "cause": "Cause Being Investigated",
      "cluster": false,
      "cust_a": {
        "masked": true,
        "val": 4
      },
      "etr": "",
      "start": "2024-07-31T11:53:32-0300"
    },
    "geom": {
      "p": [
        "wlg}GhfbpJ"
      ]
    },
    "id": "7",
    "title": "Outage Information"
  }
]
