[
  {
    "desc": {
      "cause": "Cause Being Investigated",
      "cluster": false,
      "cust_a": {
        "masked": true,
        "val": 4
      },
      "etr": "2023-10-08T21:45:00-0300",
      "start": "2023-10-08T16:59:11-0300"
    },
    "geom": {
      "p": [
        "i|nqG~atjK"
      ]
    },
    "id": "10",
    "title": "Outage Information"
  },
  {
    "desc": {
      "cause": "Cause Being Investigated",
      "cluster": false,
      "cust_a": {
        "val": 83
      },
      "etr": "2023-10-08T21:45:00-0300",
      "start": "2023-10-08T16:59:14-0300"
    },
    "geom": {
      "a": [
        "gonqGtqfkK{DjPcCQmCeCoB}DxEsO~@yBbHvL"
      ],
      "p": [
        "axnqG|tfkK"
      ]
    },
    "id": "11",
    "title": "Outage Information"
  },
  {
    "desc": {
      "cause": "Cause Being Investigated",
      "cluster": false,
      "cust_a": {
        "masked": true,
        "val": 4
      },
      "etr": "2023-10-08T21:45:00-0300",
      "start": "2023-10-08T17:00:13-0300"
    },
    "geom": {
      "p": [
        "kzjqGpx_kK"
      ]
    },
    "id": "13",
    "title": "Outage Information"
  },
  {
    "desc": {
      "cause": "Cause Being Investigated",
      "cluster": false,
      "cust_a": {
        "masked": true,
        "val": 4
      },
      "etr": "2023-10-08T21:45:00-0300",
      "start": "2023-10-08T17:00:16-0300"
    },
    "geom": {
      "p": [
        "ktkqGxl~jK"
      ]
    },
    "id": "14",
    "title": "Outage Information"
  },
  {
    "desc": {
      "cluster": true,
      "cust_a": {
        "masked": true,
        "val": 4
      },
      "n_out": 2,
      "outages": [
        {
          "cause": "Cause Being Investigated",
          "cluster": false,
          "cust_a": {
            "masked": true,
            "val": 4
          },
          "etr": "2023-10-08T21:45:00-0300",
          "start": "2023-10-08T17:00:03-0300"
        },
        {
          "cause": "Cause Being Investigated",
          "cluster": false,
          "cust_a": {
            "masked": true,
            "val": 4
          },
          "etr": "2023-10-08T21:45:00-0300",
          "start": "2023-10-08T16:59:39-0300"
        }
      ]
    },
    "geom": {
      "p": [
        "qbmqGjvhkK"
      ]
    },
    "id": "14-1",
    "title": "Area Outage"
  },
  {
    "desc": {
      "cluster": true,
      "cust_a": {
        "masked": true,
        "val": 4
      },
      "n_out": 2,
      "outages": [
        {
          "cause": "Cause Being Investigated",
          "cluster": false,
          "cust_a": {
            "masked": true,
            "val": 4
          },
          "etr": "2023-10-08T20:45:00-0300",
          "start": "2023-10-08T16:59:11-0300"
        },
        {
          "cause": "Cause Being Investigated",
          "cluster": false,
          "cust_a": {
            "masked": true,
            "val": 4
          },
          "etr": "2023-10-08T21:00:00-0300",
          "start": "2023-10-08T16:59:33-0300"
        }
      ]
    },
    "geom": {
      "p": [
        "ccoqG~whkK"
      ]
    },
    "id": "14-2",
    "title": "Area Outage"
  },
  {
    "desc": {
      "cause": "Cause Being Investigated",
      "cluster": false,
      "cust_a": {
        "masked": true,
        "val": 4
      },
      "etr": "2023-10-08T21:45:00-0300",
      "start": "2023-10-08T16:59:42-0300"
    },
    "geom": {
      "p": [
        "}}iqGtfbkK"
      ]
    },
    "id": "15",
    "title": "Outage Information"
  },
  {
    "desc": {
      "cause": "Cause Being Investigated",
      "cluster": false,
      "cust_a": {
        "masked": true,
        "val": 4
      },
      "etr": "2023-10-08T21:45:00-0300",
      "start": "2023-10-08T17:00:04-0300"
    },
    "geom": {
      "p": [
        "s}nqGzmgkK"
      ]
    },
    "id": "16",
    "title": "Outage Information"
  },
  {
    "desc": {
      "cause": "Cause Being Investigated",
      "cluster": false,
      "cust_a": {
        "val": 70
      },
      "etr": "2023-10-08T21:45:00-0300",
      "start": "2023-10-08T16:59:12-0300"
    },
    "geom": {
      "a": [
        "uxmqGvhfkKwHv[cAwMvEsIbDkB"
      ],
      "p": [
        "s_nqGzufkK"
      ]
    },
    "id": "17",
    "title": "Outage Information"
  },
  {
    "desc": {
      "cause": "Cause Being Investigated",
      "cluster": false,
      "cust_a": {
        "masked": true,
        "val": 4
      },
      "etr": "2023-10-08T21:30:00-0300",
      "start": "2023-10-08T16:48:18-0300"
    },
    "geom": {
      "p": [
        "od~qGvkzjK"
      ]
    },
    "id": "18",
    "title": "Outage Information"
  },
  {
    "desc": {
      "cause": "Cause Being Investigated",
      "cluster": false,
      "cust_a": {
        "masked": true,
        "val": 4
      },
      "etr": "2023-10-08T20:30:00-0300",
      "start": "2023-10-08T16:36:49-0300"
    },
    "geom": {
      "p": [
        "_{dtGfvphK"
      ]
    },
    "id": "19",
    "title": "Outage Information"
  },
  {
    "desc": {
      "cause": "Cause Being Investigated",
      "cluster": false,
      "cust_a": {
        "masked": true,
        "val": 4
      },
      "etr": "2023-10-08T21:45:00-0300",
      "start": "2023-10-08T17:00:04-0300"
    },
    "geom": {
      "p": [
        "czlqGnyakK"
      ]
    },
    "id": "2",
    "title": "Outage Information"
  },
  {
    "desc": {
      "cause": "Cause Being Investigated",
      "cluster": false,
      "cust_a": {
        "masked": true,
        "val": 4
      },
      "etr": "2023-10-08T21:00:00-0300",
      "start": "2023-10-08T15:13:34-0300"
    },
    "geom": {
      "p": [
        "}k|xGhs}lJ"
      ]
    },
    "id": "20",
    "title": "Outage Information"
  },
  {
    "desc": {
      "cause": "Cause Being Investigated",
      "cluster": false,
      "cust_a": {
        "masked": true,
        "val": 4
      },
      "etr": "2023-10-08T21:00:00-0300",
      "start": "2023-10-08T13:38:46-0300"
    },
    "geom": {
      "p": [
        "}zbxGr`_pJ"
      ]
    },
    "id": "21",
    "title": "Outage Information"
  },
  {
    "desc": {
      "cause": "Cause Being Investigated",
      "cluster": false,
      "cust_a": {
        "masked": true,
        "val": 4
      },
      "etr": "2023-10-08T21:00:00-0300",
      "start": "2023-10-08T13:34:41-0300"
    },
    "geom": {
      "p": [
        "yypuGp}jqJ"
      ]
    },
    "id": "23",
    "title": "Outage Information"
  },
  {
    "desc": {
      "cause": "Cause Being Investigated",
      "cluster": false,
      "cust_a": {
        "masked": true,
        "val": 4
      },
      "etr": "2023-10-08T21:00:00-0300",
      "start": "2023-10-08T13:35:48-0300"
    },
    "geom": {
      "p": [
        "u~amGjzohK"
      ]
    },
    "id": "24",
    "title": "Outage Information"
  },
  {
    "desc": {
      "cause": "Cause Being Investigated",
      "cluster": false,
      "cust_a": {
        "masked": true,
        "val": 4
      },
      "etr": "2023-10-08T21:00:00-0300",
      "start": "2023-10-08T14:59:02-0300"
    },
    "geom": {
      "p": [
        "iy`yG`jwnJ"
      ]
    },
    "id": "25",
    "title": "Outage Information"
  },
  {
    "desc": {
      "cause": "Cause Being Investigated",
      "cluster": false,
      "cust_a": {
        "masked": true,
        "val": 4
      },
      "etr": "2023-10-08T21:00:00-0300",
      "start": "2023-10-08T14:23:49-0300"
    },
    "geom": {
      "p": [
        "_eiyGbrwmJ"
      ]
    },
    "id": "26",
    "title": "Outage Information"
  },
  {
    "desc": {
      "cause": "Cause Being Investigated",
      "cluster": false,
      "cust_a": {
        "val": 6
      },
      "etr": "2023-10-08T21:00:00-0300",
      "start": "2023-10-08T13:02:08-0300"
    },
    "geom": {
      "p": [
        "aaeyGttpnJ"
      ]
    },
    "id": "27",
    "title": "Outage Information"
  },
  {
    "desc": {
      "cause": "Cause Being Investigated",
      "cluster": false,
      "cust_a": {
        "masked": true,
        "val": 4
      },
      "etr": "2023-10-08T21:00:00-0300",
      "start": "2023-10-08T15:27:00-0300"
    },
    "geom": {
      "p": [
        "qocyGdfrnJ"
      ]
    },
    "id": "28",
    "title": "Outage Information"
  },
  {
    "desc": {
      "cause": "Cause Being Investigated",
      "cluster": false,
      "cust_a": {
        "masked": true,
        "val": 4
      },
      "etr": "2023-10-08T21:45:00-0300",
      "start": "2023-10-08T15:08:20-0300"
    },
    "geom": {
      "p": [
        "grlxGfijlJ"
      ]
    },
    "id": "29",
    "title": "Outage Information"
  },
  {
    "desc": {
      "cause": "Cause Being Investigated",
      "cluster": false,
      "cust_a": {
        "masked": true,
        "val": 4
      },
      "etr": "2023-10-08T21:45:00-0300",
      "start": "2023-10-08T16:59:43-0300"
    },
    "geom": {
      "p": [
        "oqjqGjrbkK"
      ]
    },
    "id": "3",
    "title": "Outage Information"
  },
  {
    "desc": {
      "cause": "High Winds and Rain",
      "cluster": false,
      "cust_a": {
        "val": 2121
      },
      "etr": "2023-10-08T20:00:00-0300",
      "start": "2023-10-08T15:08:20-0300"
    },
    "geom": {
      "a": [
        "{cbwGbybmJ}O|r@_xAb{Aut_@peVqhFgkX~L_i\\fdAas@zf[oy@tkKd{\\j@~P"
      ],
      "p": [
        "m|zwGlp}lJ"
      ]
    },
    "id": "30",
    "title": "Outage Information"
  },
  {
    "desc": {
      "cause": "Cause Being Investigated",
      "cluster": false,
      "cust_a": {
        "masked": true,
        "val": 4
      },
      "etr": "2023-10-08T20:00:00-0300",
      "start": "2023-10-08T16:13:08-0300"
    },
    "geom": {
      "p": [
        "wgbvGzpy_K"
      ]
    },
    "id": "31",
    "title": "Outage Information"
  },
  {
    "desc": {
      "cause": "Damage to Overhead Equipment",
      "cluster": false,
      "cust_a": {
        "val": 2035
      },
      "etr": "2023-10-08T20:00:00-0300",
      "start": "2023-10-08T16:19:08-0300"
    },
    "geom": {
      "a": [
        "_x_vGboxnJch`@~sRm|Fyi@mpMemEigGuk\\kwAclL~xCwoEnV}Czqe@h|KffU|tQ`Lf_E"
      ],
      "p": [
        "_tdwGpmpnJ"
      ]
    },
    "id": "32",
    "title": "Outage Information"
  },
  {
    "desc": {
      "cause": "Cause Being Investigated",
      "cluster": false,
      "cust_a": {
        "masked": true,
        "val": 4
      },
      "etr": "2023-10-08T21:15:00-0300",
      "start": "2023-10-08T16:03:39-0300"
    },
    "geom": {
      "p": [
        "odkvGhnwpJ"
      ]
    },
    "id": "34",
    "title": "Outage Information"
  },
  {
    "desc": {
      "cause": "Cause Being Investigated",
      "cluster": false,
      "cust_a": {
        "masked": true,
        "val": 4
      },
      "etr": "2023-10-08T20:45:00-0300",
      "start": "2023-10-08T15:42:45-0300"
    },
    "geom": {
      "p": [
        "wugvGdz}pJ"
      ]
    },
    "id": "35",
    "title": "Outage Information"
  },
  {
    "desc": {
      "cause": "Cause Being Investigated",
      "cluster": false,
      "cust_a": {
        "masked": true,
        "val": 4
      },
      "etr": "2023-10-08T21:30:00-0300",
      "start": "2023-10-08T16:16:01-0300"
    },
    "geom": {
      "p": [
        "}njvGvywpJ"
      ]
    },
    "id": "36",
    "title": "Outage Information"
  },
  {
    "desc": {
      "cause": "Cause Being Investigated",
      "cluster": false,
      "cust_a": {
        "masked": true,
        "val": 4
      },
      "etr": "2023-10-08T20:45:00-0300",
      "start": "2023-10-08T15:31:00-0300"
    },
    "geom": {
      "p": [
        "akgvG~d~pJ"
      ]
    },
    "id": "37",
    "title": "Outage Information"
  },
  {
    "desc": {
      "cause": "Cause Being Investigated",
      "cluster": false,
      "cust_a": {
        "masked": true,
        "val": 4
      },
      "etr": "2023-10-08T20:30:00-0300",
      "start": "2023-10-08T15:56:12-0300"
    },
    "geom": {
      "p": [
        "cwloGls}eK"
      ]
    },
    "id": "38",
    "title": "Outage Information"
  },
  {
    "desc": {
      "cause": "Cause Being Investigated",
      "cluster": false,
      "cust_a": {
        "masked": true,
        "val": 4
      },
      "etr": "2023-10-08T21:00:00-0300",
      "start": "2023-10-08T15:58:00-0300"
    },
    "geom": {
      "p": [
        "uqqxG~{llJ"
      ]
    },
    "id": "39",
    "title": "Outage Information"
  },
  {
    "desc": {
      "cause": "Cause Being Investigated",
      "cluster": false,
      "cust_a": {
        "masked": true,
        "val": 4
      },
      "etr": "2023-10-08T21:45:00-0300",
      "start": "2023-10-08T17:00:23-0300"
    },
    "geom": {
      "p": [
        "yjjqG|{akK"
      ]
    },
    "id": "4",
    "title": "Outage Information"
  },
  {
    "desc": {
      "cause": "Cause Being Investigated",
      "cluster": false,
      "cust_a": {
        "val": 21
      },
      "etr": "2023-10-08T20:15:00-0300",
      "start": "2023-10-08T13:59:17-0300"
    },
    "geom": {
      "a": [
        "ivqvGfseuJsF`Lkf@~JgjAu@kn@q[_wC}tElxA|a@`mE~fCbYdo@"
      ],
      "p": [
        "ijvvGticuJ"
      ]
    },
    "id": "40",
    "title": "Outage Information"
  },
  {
    "desc": {
      "cause": "Cause Being Investigated",
      "cluster": false,
      "cust_a": {
        "masked": true,
        "val": 4
      },
      "etr": "2023-10-08T20:00:00-0300",
      "start": "2023-10-08T14:48:49-0300"
    },
    "geom": {
      "p": [
        "ijyxGlr`oJ"
      ]
    },
    "id": "41",
    "title": "Outage Information"
  },
  {
    "desc": {
      "cause": "Cause Being Investigated",
      "cluster": false,
      "cust_a": {
        "val": 5
      },
      "etr": "2023-10-09T00:15:00-0300",
      "start": "2023-10-08T12:07:29-0300"
    },
    "geom": {
      "p": [
        "c~`yG~dunJ"
      ]
    },
    "id": "42",
    "title": "Outage Information"
  },
  {
    "desc": {
      "cause": "Cause Being Investigated",
      "cluster": false,
      "cust_a": {
        "masked": true,
        "val": 4
      },
      "etr": "2023-10-08T21:45:00-0300",
      "start": "2023-10-08T16:59:51-0300"
    },
    "geom": {
      "p": [
        "{}jqG`~ckK"
      ]
    },
    "id": "5",
    "title": "Outage Information"
  },
  {
    "desc": {
      "cause": "Cause Being Investigated",
      "cluster": false,
      "cust_a": {
        "masked": true,
        "val": 4
      },
      "etr": "2023-10-08T21:45:00-0300",
      "start": "2023-10-08T16:59:54-0300"
    },
    "geom": {
      "p": [
        "_hoqGfirjK"
      ]
    },
    "id": "6",
    "title": "Outage Information"
  },
  {
    "desc": {
      "cause": "Cause Being Investigated",
      "cluster": false,
      "cust_a": {
        "masked": true,
        "val": 4
      },
      "etr": "2023-10-08T21:45:00-0300",
      "start": "2023-10-08T17:00:04-0300"
    },
    "geom": {
      "p": [
        "cimqGj`xjK"
      ]
    },
    "id": "8",
    "title": "Outage Information"
  }
]
