[
  {
    "desc": {
      "cause": "Cause Being Investigated",
      "cluster": false,
      "cust_a": {
        "masked": true,
        "val": 4
      },
      "etr": "2026-02-12T23:30:00-0400",
      "start": "2026-02-12T16:17:00-0400"
    },
    "geom": {
      "p": [
        "_x_rGnkr~J"
      ]
    },
    "id": "1",
    "title": "Outage Information"
  },
  {
    "desc": {
      "cause": "Cause Being Investigated",
      "cluster": false,
      "cust_a": {
        "val": 41
      },
      "etr": "2026-02-12T21:00:00-0400",
      "start": "2026-02-12T16:16:48-0400"
    },
    "geom": {
      "a": [
        "c_zoG|imbK_Dt@}B}G`Dq@zBxG"
      ],
      "p": [
        "qczoGhfmbK"
      ]
    },
    "id": "2",
    "title": "Outage Information"
  },
  {
    "desc": {
      "cause": "Cause Being Investigated",
      "cluster": false,
      "cust_a": {
        "masked": true,
        "val": 4
      },
      "etr": "2026-02-12T21:30:00-0400",
      "start": "2026-02-12T15:47:39-0400"
    },
    "geom": {
      "p": [
        "oowoG~cybK"
      ]
    },
    "id": "3",
    "title": "Outage Information"
  },
  {
    "desc": {
      "cause": "Cause Being Investigated",
      "cluster": false,
      "cust_a": {
        "masked": true,
        "val": 4
      },
      "etr": "2026-02-12T21:30:00-0400",
      "start": "2026-02-12T14:19:13-0400"
    },
    "geom": {
      "p": [
        "oshnGn{jhK"
      ]
    },
    "id": "4",
    "title": "Outage Information"
  },
  {
    "desc": {
      "cause": "Cause Being Investigated",
      "cluster": false,
      "cust_a": {
        "masked": true,
        "val": 4
      },
      "etr": "2026-02-12T21:30:00-0400",
      "start": "2026-02-12T14:15:03-0400"
    },
    "geom": {
      "p": [
        "qnhnGhnjhK"
      ]
    },
    "id": "5",
    "title": "Outage Information"
  },
  {
    "desc": {
      "cause": "Cause Being Investigated",
      "cluster": false,
      "cust_a": {
        "masked": true,
        "val": 4
      },
      "etr": "2026-02-12T18:30:00-0400",
      "start": "2026-02-12T11:21:18-0400"
    },
    "geom": {
      "p": [
        "ocgpG~vv`K"
      ]
    },
    "id": "6",
    "title": "Outage Information"
  },
  {
    "desc": {
      "cause": "Cause Being Investigated",
      "cluster": false,
      "cust_a": {
        "masked": true,
        "val": 4
      },
      "etr": "2026-02-14T20:00:00-0400",
      "start": "2026-02-10T19:35:36-0400"
    },
    "geom": {
      "p": [
        "sinuGvb{~J"
      ]
    },
    "id": "7",
    "title": "Outage Information"
  },
  {
    "desc": {
      "cause": "Cause Being Investigated",
      "cluster": false,
      "cust_a": {
        "masked": true,
        "val": 4
      },
      "etr": "2026-02-13T12:00:00-0400",
      "start": "2026-01-31T10:14:37-0400"
    },
    "geom": {
      "p": [
        "_tqoGnnhfK"
      ]
    },
    "id": "8",
    "title": "Outage Information"
  }
]
