[
  {
    "desc": {
      "cause": "Cause Being Investigated",
      "cluster": false,
      "cust_a": {
        "val": 6
      },
      "etr": "2023-05-11T03:30:00-0300",
      "start": "2023-05-10T22:50:45-0300"
    },
    "geom": {
      "p": [
        "_hoiGtlrpK"
      ]
    },
    "id": "1",
    "title": "Outage Information"
  },
  {
    "desc": {
      "cause": "Cause Being Investigated",
      "cluster": false,
      "cust_a": {
        "masked": true,
        "val": 4
      },
      "etr": "",
      "start": "2023-05-10T13:25:00-0300"
    },
    "geom": {
      "p": [
        "i}gtGrz_yJ"
      ]
    },
    "id": "2",
    "title": "Outage Information"
  }
]
