[
  {
    "desc": {
      "cause": "Cause Being Investigated",
      "cluster": false,
      "cust_a": {
        "masked": true,
        "val": 4
      },
      "etr": "2025-06-05T14:45:00-0300",
      "start": "2025-06-05T10:58:00-0300"
    },
    "geom": {
      "p": [
        "{_kuGp{_wJ"
      ]
    },
    "id": "1",
    "title": "Outage Information"
  },
  {
    "desc": {
      "cause": "Planned Maintenance",
      "cluster": false,
      "cust_a": {
        "val": 96
      },
      "etr": "2025-06-05T16:00:00-0300",
      "start": "2025-06-05T09:05:34-0300"
    },
    "geom": {
      "a": [
        "}qroGxancKKdFuT}_@p@{SX[nGaGdJbo@?lF"
      ],
      "p": [
        "_}roGpgmcK"
      ]
    },
    "id": "10",
    "title": "Outage Information"
  },
  {
    "desc": {
      "cause": "Planned Maintenance",
      "cluster": false,
      "cust_a": {
        "val": 36
      },
      "etr": "2025-06-05T16:30:00-0300",
      "start": "2025-06-05T09:04:05-0300"
    },
    "geom": {
      "a": [
        "kz`tGvicgKyAzDkDbA{k@gkE_Dey@RqfB~JeN~NhkArO|~BVbE`KxaD"
      ],
      "p": [
        "gzatGxh}fK"
      ]
    },
    "id": "11",
    "title": "Outage Information"
  },
  {
    "desc": {
      "cause": "Planned Maintenance",
      "cluster": false,
      "cust_a": {
        "val": 203
      },
      "etr": "2025-06-05T13:00:00-0300",
      "start": "2025-06-05T08:59:08-0300"
    },
    "geom": {
      "a": [
        "s}evG`tz}Jer@hbHcDrD}C~Bsr@_aA{BkjKfGqfCvE~Dpg@prAfw@rrCbA~RxAxe@"
      ],
      "p": [
        "mbhvG~c{}J"
      ]
    },
    "id": "12",
    "title": "Outage Information"
  },
  {
    "desc": {
      "cause": "Cause Being Investigated",
      "cluster": false,
      "cust_a": {
        "masked": true,
        "val": 4
      },
      "etr": "2025-06-05T13:15:00-0300",
      "start": "2025-06-05T08:06:00-0300"
    },
    "geom": {
      "p": [
        "iwpwGz}lpJ"
      ]
    },
    "id": "13",
    "title": "Outage Information"
  },
  {
    "desc": {
      "cause": "Cause Being Investigated",
      "cluster": false,
      "cust_a": {
        "masked": true,
        "val": 4
      },
      "etr": "2025-06-05T15:15:00-0300",
      "start": "2025-06-05T11:12:00-0300"
    },
    "geom": {
      "p": [
        "ykhrGtz_hK"
      ]
    },
    "id": "2",
    "title": "Outage Information"
  },
  {
    "desc": {
      "cause": "Cause Being Investigated",
      "cluster": false,
      "cust_a": {
        "masked": true,
        "val": 4
      },
      "etr": "2025-06-05T14:30:00-0300",
      "start": "2025-06-05T10:39:00-0300"
    },
    "geom": {
      "p": [
        "cfnrGv{|`K"
      ]
    },
    "id": "3",
    "title": "Outage Information"
  },
  {
    "desc": {
      "cause": "Cause Being Investigated",
      "cluster": false,
      "cust_a": {
        "masked": true,
        "val": 4
      },
      "etr": "2025-06-05T14:15:00-0300",
      "start": "2025-06-05T09:41:00-0300"
    },
    "geom": {
      "p": [
        "}i`lGt_aiK"
      ]
    },
    "id": "4",
    "title": "Outage Information"
  },
  {
    "desc": {
      "cause": "Cause Being Investigated",
      "cluster": false,
      "cust_a": {
        "masked": true,
        "val": 4
      },
      "etr": "2025-06-05T13:30:00-0300",
      "start": "2025-06-05T10:16:00-0300"
    },
    "geom": {
      "p": [
        "qxkuGlkg}J"
      ]
    },
    "id": "5",
    "title": "Outage Information"
  },
  {
    "desc": {
      "cause": "Cause Being Investigated",
      "cluster": false,
      "cust_a": {
        "masked": true,
        "val": 4
      },
      "etr": "2025-06-05T13:30:00-0300",
      "start": "2025-06-05T10:17:22-0300"
    },
    "geom": {
      "p": [
        "_rdoGnudcK"
      ]
    },
    "id": "6",
    "title": "Outage Information"
  },
  {
    "desc": {
      "cause": "Cause Being Investigated",
      "cluster": false,
      "cust_a": {
        "masked": true,
        "val": 4
      },
      "etr": "2025-06-05T16:30:00-0300",
      "start": "2025-06-05T10:17:00-0300"
    },
    "geom": {
      "p": [
        "{troGriecK"
      ]
    },
    "id": "7",
    "title": "Outage Information"
  },
  {
    "desc": {
      "cause": "Cause Being Investigated",
      "cluster": false,
      "cust_a": {
        "val": 87
      },
      "etr": "2025-06-05T14:15:00-0300",
      "start": "2025-06-05T10:08:00-0300"
    },
    "geom": {
      "a": [
        "mnroG|kdcKgO|T~CuFfJgM"
      ],
      "p": [
        "qwroG~wdcK"
      ]
    },
    "id": "8",
    "title": "Outage Information"
  },
  {
    "desc": {
      "cause": "Planned Maintenance",
      "cluster": false,
      "cust_a": {
        "val": 34
      },
      "etr": "2025-06-05T12:15:00-0300",
      "start": "2025-06-05T09:19:54-0300"
    },
    "geom": {
      "p": [
        "acvoGv~acK"
      ]
    },
    "id": "9",
    "title": "Outage Information"
  }
]
