[
  {
    "desc": {
      "cause": "Cause Being Investigated",
      "cluster": false,
      "cust_a": {
        "masked": true,
        "val": 4
      },
      "etr": "2024-09-18T19:15:00-0300",
      "start": "2024-09-18T16:11:00-0300"
    },
    "geom": {
      "p": [
        "g`jsGlcbbK"
      ]
    },
    "id": "1",
    "title": "Outage Information"
  },
  {
    "desc": {
      "cause": "Cause Being Investigated",
      "cluster": false,
      "cust_a": {
        "val": 6
      },
      "etr": "2024-09-18T20:30:00-0300",
      "start": "2024-09-18T12:39:02-0300"
    },
    "geom": {
      "p": [
        "{n~qGziteK"
      ]
    },
    "id": "2",
    "title": "Outage Information"
  },
  {
    "desc": {
      "cause": "Cause Being Investigated",
      "cluster": false,
      "cust_a": {
        "masked": true,
        "val": 4
      },
      "etr": "2024-09-18T19:15:00-0300",
      "start": "2024-09-18T15:18:00-0300"
    },
    "geom": {
      "p": [
        "mo}qGddclK"
      ]
    },
    "id": "3",
    "title": "Outage Information"
  },
  {
    "desc": {
      "cause": "Cause Being Investigated",
      "cluster": false,
      "cust_a": {
        "masked": true,
        "val": 4
      },
      "etr": "2024-09-18T18:30:00-0300",
      "start": "2024-09-18T15:23:28-0300"
    },
    "geom": {
      "p": [
        "m{zsGzkpaK"
      ]
    },
    "id": "4",
    "title": "Outage Information"
  },
  {
    "desc": {
      "cause": "Cause Being Investigated",
      "cluster": false,
      "cust_a": {
        "masked": true,
        "val": 4
      },
      "etr": "2024-09-18T19:45:00-0300",
      "start": "2024-09-18T14:32:26-0300"
    },
    "geom": {
      "p": [
        "i`lvG~rnnJ"
      ]
    },
    "id": "5",
    "title": "Outage Information"
  }
]
