[
  {
    "desc": {
      "cause": "Cause Being Investigated",
      "cluster": false,
      "cust_a": {
        "masked": true,
        "val": 4
      },
      "etr": "2025-07-29T11:30:00-0300",
      "start": "2025-07-29T07:36:00-0300"
    },
    "geom": {
      "p": [
        "yl`vGvtp`K"
      ]
    },
    "id": "1",
    "title": "Outage Information"
  },
  {
    "desc": {
      "cause": "Cause Being Investigated",
      "cluster": false,
      "cust_a": {
        "val": 5
      },
      "etr": "2025-07-29T10:30:00-0300",
      "start": "2025-07-29T07:06:20-0300"
    },
    "geom": {
      "p": [
        "_v_pGja}aK"
      ]
    },
    "id": "2",
    "title": "Outage Information"
  },
  {
    "desc": {
      "cause": "Cause Being Investigated",
      "cluster": false,
      "cust_a": {
        "masked": true,
        "val": 4
      },
      "etr": "2025-07-29T11:30:00-0300",
      "start": "2025-07-29T06:07:00-0300"
    },
    "geom": {
      "p": [
        "ivkuGtnusJ"
      ]
    },
    "id": "3",
    "title": "Outage Information"
  },
  {
    "desc": {
      "cause": "Cause Being Investigated",
      "cluster": false,
      "cust_a": {
        "masked": true,
        "val": 4
      },
      "etr": "2025-07-29T09:15:00-0300",
      "start": "2025-07-29T05:08:00-0300"
    },
    "geom": {
      "p": [
        "sigyG~awmJ"
      ]
    },
    "id": "4",
    "title": "Outage Information"
  },
  {
    "desc": {
      "cause": "Cause Being Investigated",
      "cluster": false,
      "cust_a": {
        "masked": true,
        "val": 4
      },
      "etr": "2025-08-22T15:45:00-0300",
      "start": "2025-07-17T21:13:37-0300"
    },
    "geom": {
      "p": [
        "}`pmG~nbkK"
      ]
    },
    "id": "5",
    "title": "Outage Information"
  }
]
