[
  {
    "desc": {
      "cause": "Cause Being Investigated",
      "cluster": false,
      "cust_a": {
        "masked": true,
        "val": 4
      },
      "etr": "2024-10-23T18:00:00-0300",
      "start": "2024-10-23T14:41:32-0300"
    },
    "geom": {
      "p": [
        "syvoGdmdcK"
      ]
    },
    "id": "1",
    "title": "Outage Information"
  },
  {
    "desc": {
      "cause": "Cause Being Investigated",
      "cluster": false,
      "cust_a": {
        "masked": true,
        "val": 4
      },
      "etr": "2024-10-23T17:00:00-0300",
      "start": "2024-10-23T08:14:00-0300"
    },
    "geom": {
      "p": [
        "}}_rGxrxiK"
      ]
    },
    "id": "2",
    "title": "Outage Information"
  },
  {
    "desc": {
      "cause": "Cause Being Investigated",
      "cluster": false,
      "cust_a": {
        "masked": true,
        "val": 4
      },
      "etr": "2024-10-23T16:45:00-0300",
      "start": "2024-10-23T12:32:00-0300"
    },
    "geom": {
      "p": [
        "ob`yGzswnJ"
      ]
    },
    "id": "3",
    "title": "Outage Information"
  },
  {
    "desc": {
      "cause": "Cause Being Investigated",
      "cluster": false,
      "cust_a": {
        "masked": true,
        "val": 4
      },
      "etr": "2024-10-23T17:00:00-0300",
      "start": "2024-10-23T12:47:04-0300"
    },
    "geom": {
      "p": [
        "anqxGfuinJ"
      ]
    },
    "id": "4",
    "title": "Outage Information"
  },
  {
    "desc": {
      "cause": "Transmission Interruption",
      "cluster": false,
      "cust_a": {
        "val": 9989
      },
      "etr": "2024-10-23T18:45:00-0300",
      "start": "2024-10-23T12:29:33-0300"
    },
    "geom": {
      "a": [
        "sskxGt_dmJgiOtkNkgDry@w^q`MoG}tDbNapAlK_v@rtD_lPv}@ixB~mAvSpDr@|m@p[fpCp|Abp@fn@zCdE~e@jt@`FxLpZv}@pu@tuP"
      ],
      "p": [
        "iwwxGjh~lJ"
      ]
    },
    "id": "5",
    "title": "Outage Information"
  },
  {
    "desc": {
      "cause": "Planned Maintenance",
      "cluster": false,
      "cust_a": {
        "val": 26
      },
      "etr": "2024-10-23T16:45:00-0300",
      "start": "2024-10-23T09:27:33-0300"
    },
    "geom": {
      "a": [
        "mxpnG`jtdKcC|c@{SpC|@sKtDeMlOuX\\~I"
      ],
      "p": [
        "ccqnGp~tdK"
      ]
    },
    "id": "6",
    "title": "Outage Information"
  }
]
